pyscrape/__init__.py
pyscrape/http.py
pyscrape/mixins.py
pyscrape/session.py
pyscrape/webkit.py
pyscrape/xvfb.py
scrapejs-0.0.1.1.dist-info/DESCRIPTION.rst
scrapejs-0.0.1.1.dist-info/METADATA
scrapejs-0.0.1.1.dist-info/RECORD
scrapejs-0.0.1.1.dist-info/WHEEL
scrapejs-0.0.1.1.dist-info/entry_points.txt
scrapejs-0.0.1.1.dist-info/metadata.json
scrapejs-0.0.1.1.dist-info/top_level.txt
